Workbook

Sheet README
A1: Excel & Pivot lessons — worked solutions
A2: Try each exercise in orders.xlsx first. Then compare with this workbook.
A3: Sheets: Orders (solved) = IF, IFS, AND/OR, XLOOKUP, INDEX/MATCH, discount, conditional formatting.
A4: Summary = SUMIFS / COUNTIFS / AVERAGEIFS tables and checks.
A5: FILTER & LET = dynamic-array formulas to type (Microsoft 365 / Excel 2021+).
A6: Model = What-If model, scenario grid and Goal Seek answers.
A7: PivotTables and slicers are not included: build them yourself by following the Pivot lessons.
A8: XLOOKUP and IFS need Excel 2019+/365; INDEX/MATCH columns work in every version.

Sheet Orders (solved)
A1: order_id | B1: order_date | C1: customer | D1: region | E1: category | F1: product | G1: quantity | H1: unit_price | I1: status | J1: value | K1: counts_as_sale | L1: size | M1: size_ifs | N1: priority | O1: follow_up | P1: key_delivery | Q1: list_price_xlookup | R1: list_price_index_match | S1: discount | T1: segment | U1: supplier
A2: 1 | B2: 46027 | C2: Rahim Traders | D2: Dhaka | E2: Fabric | F2: Cotton Twill | G2: 120 | H2: 3.5 | I2: Delivered | J2: =G2*H2 | K2: =IF(I2="Cancelled","No","Yes") | L2: =IF(J2>=1000,"Large",IF(J2>=500,"Medium","Small")) | M2: =_xlfn.IFS(J2>=1000,"Large",J2>=500,"Medium",TRUE,"Small") | N2: =IF(AND(D2="Dhaka",J2>=1000),"Priority","Normal") | O2: =IF(OR(I2="Shipped",I2="Pending"),"Follow up","") | P2: =IF(AND(I2="Delivered",J2>=1000),"Key delivery","-") | Q2: =_xlfn.XLOOKUP(F2,Products!$A$2:$A$7,Products!$C$2:$C$7,"Not found") | R2: =INDEX(Products!$C$2:$C$7,MATCH(F2,Products!$A$2:$A$7,0)) | S2: =1-H2/R2 | T2: =INDEX(Customers!$C$2:$C$7,MATCH(C2,Customers!$B$2:$B$7,0)) | U2: =INDEX(Products!$D$2:$D$7,MATCH(F2,Products!$A$2:$A$7,0))
A3: 2 | B3: 46030 | C3: Karim Garments | D3: Chattogram | E3: Trims | F3: Metal Buttons | G3: 5000 | H3: 0.04 | I3: Delivered | J3: =G3*H3 | K3: =IF(I3="Cancelled","No","Yes") | L3: =IF(J3>=1000,"Large",IF(J3>=500,"Medium","Small")) | M3: =_xlfn.IFS(J3>=1000,"Large",J3>=500,"Medium",TRUE,"Small") | N3: =IF(AND(D3="Dhaka",J3>=1000),"Priority","Normal") | O3: =IF(OR(I3="Shipped",I3="Pending"),"Follow up","") | P3: =IF(AND(I3="Delivered",J3>=1000),"Key delivery","-") | Q3: =_xlfn.XLOOKUP(F3,Products!$A$2:$A$7,Products!$C$2:$C$7,"Not found") | R3: =INDEX(Products!$C$2:$C$7,MATCH(F3,Products!$A$2:$A$7,0)) | S3: =1-H3/R3 | T3: =INDEX(Customers!$C$2:$C$7,MATCH(C3,Customers!$B$2:$B$7,0)) | U3: =INDEX(Products!$D$2:$D$7,MATCH(F3,Products!$A$2:$A$7,0))
A4: 3 | B4: 46034 | C4: Nova Apparel | D4: Dhaka | E4: Fabric | F4: Denim 12oz | G4: 300 | H4: 5.2 | I4: Delivered | J4: =G4*H4 | K4: =IF(I4="Cancelled","No","Yes") | L4: =IF(J4>=1000,"Large",IF(J4>=500,"Medium","Small")) | M4: =_xlfn.IFS(J4>=1000,"Large",J4>=500,"Medium",TRUE,"Small") | N4: =IF(AND(D4="Dhaka",J4>=1000),"Priority","Normal") | O4: =IF(OR(I4="Shipped",I4="Pending"),"Follow up","") | P4: =IF(AND(I4="Delivered",J4>=1000),"Key delivery","-") | Q4: =_xlfn.XLOOKUP(F4,Products!$A$2:$A$7,Products!$C$2:$C$7,"Not found") | R4: =INDEX(Products!$C$2:$C$7,MATCH(F4,Products!$A$2:$A$7,0)) | S4: =1-H4/R4 | T4: =INDEX(Customers!$C$2:$C$7,MATCH(C4,Customers!$B$2:$B$7,0)) | U4: =INDEX(Products!$D$2:$D$7,MATCH(F4,Products!$A$2:$A$7,0))
A5: 4 | B5: 46037 | C5: Rahim Traders | D5: Dhaka | E5: Trims | F5: Zippers | G5: 800 | H5: 0.3 | I5: Cancelled | J5: =G5*H5 | K5: =IF(I5="Cancelled","No","Yes") | L5: =IF(J5>=1000,"Large",IF(J5>=500,"Medium","Small")) | M5: =_xlfn.IFS(J5>=1000,"Large",J5>=500,"Medium",TRUE,"Small") | N5: =IF(AND(D5="Dhaka",J5>=1000),"Priority","Normal") | O5: =IF(OR(I5="Shipped",I5="Pending"),"Follow up","") | P5: =IF(AND(I5="Delivered",J5>=1000),"Key delivery","-") | Q5: =_xlfn.XLOOKUP(F5,Products!$A$2:$A$7,Products!$C$2:$C$7,"Not found") | R5: =INDEX(Products!$C$2:$C$7,MATCH(F5,Products!$A$2:$A$7,0)) | S5: =1-H5/R5 | T5: =INDEX(Customers!$C$2:$C$7,MATCH(C5,Customers!$B$2:$B$7,0)) | U5: =INDEX(Products!$D$2:$D$7,MATCH(F5,Products!$A$2:$A$7,0))
A6: 5 | B6: 46042 | C6: Delta Knit | D6: Gazipur | E6: Yarn | F6: Cotton Yarn 30s | G6: 450 | H6: 2.8 | I6: Delivered | J6: =G6*H6 | K6: =IF(I6="Cancelled","No","Yes") | L6: =IF(J6>=1000,"Large",IF(J6>=500,"Medium","Small")) | M6: =_xlfn.IFS(J6>=1000,"Large",J6>=500,"Medium",TRUE,"Small") | N6: =IF(AND(D6="Dhaka",J6>=1000),"Priority","Normal") | O6: =IF(OR(I6="Shipped",I6="Pending"),"Follow up","") | P6: =IF(AND(I6="Delivered",J6>=1000),"Key delivery","-") | Q6: =_xlfn.XLOOKUP(F6,Products!$A$2:$A$7,Products!$C$2:$C$7,"Not found") | R6: =INDEX(Products!$C$2:$C$7,MATCH(F6,Products!$A$2:$A$7,0)) | S6: =1-H6/R6 | T6: =INDEX(Customers!$C$2:$C$7,MATCH(C6,Customers!$B$2:$B$7,0)) | U6: =INDEX(Products!$D$2:$D$7,MATCH(F6,Products!$A$2:$A$7,0))
A7: 6 | B7: 46055 | C7: Karim Garments | D7: Chattogram | E7: Fabric | F7: Cotton Twill | G7: 200 | H7: 3.4 | I7: Delivered | J7: =G7*H7 | K7: =IF(I7="Cancelled","No","Yes") | L7: =IF(J7>=1000,"Large",IF(J7>=500,"Medium","Small")) | M7: =_xlfn.IFS(J7>=1000,"Large",J7>=500,"Medium",TRUE,"Small") | N7: =IF(AND(D7="Dhaka",J7>=1000),"Priority","Normal") | O7: =IF(OR(I7="Shipped",I7="Pending"),"Follow up","") | P7: =IF(AND(I7="Delivered",J7>=1000),"Key delivery","-") | Q7: =_xlfn.XLOOKUP(F7,Products!$A$2:$A$7,Products!$C$2:$C$7,"Not found") | R7: =INDEX(Products!$C$2:$C$7,MATCH(F7,Products!$A$2:$A$7,0)) | S7: =1-H7/R7 | T7: =INDEX(Customers!$C$2:$C$7,MATCH(C7,Customers!$B$2:$B$7,0)) | U7: =INDEX(Products!$D$2:$D$7,MATCH(F7,Products!$A$2:$A$7,0))
A8: 7 | B8: 46059 | C8: Nova Apparel | D8: Dhaka | E8: Trims | F8: Metal Buttons | G8: 8000 | H8: 0.04 | I8: Shipped | J8: =G8*H8 | K8: =IF(I8="Cancelled","No","Yes") | L8: =IF(J8>=1000,"Large",IF(J8>=500,"Medium","Small")) | M8: =_xlfn.IFS(J8>=1000,"Large",J8>=500,"Medium",TRUE,"Small") | N8: =IF(AND(D8="Dhaka",J8>=1000),"Priority","Normal") | O8: =IF(OR(I8="Shipped",I8="Pending"),"Follow up","") | P8: =IF(AND(I8="Delivered",J8>=1000),"Key delivery","-") | Q8: =_xlfn.XLOOKUP(F8,Products!$A$2:$A$7,Products!$C$2:$C$7,"Not found") | R8: =INDEX(Products!$C$2:$C$7,MATCH(F8,Products!$A$2:$A$7,0)) | S8: =1-H8/R8 | T8: =INDEX(Customers!$C$2:$C$7,MATCH(C8,Customers!$B$2:$B$7,0)) | U8: =INDEX(Products!$D$2:$D$7,MATCH(F8,Products!$A$2:$A$7,0))
A9: 8 | B9: 46064 | C9: Delta Knit | D9: Gazipur | E9: Yarn | F9: Polyester Yarn | G9: 600 | H9: 2.1 | I9: Delivered | J9: =G9*H9 | K9: =IF(I9="Cancelled","No","Yes") | L9: =IF(J9>=1000,"Large",IF(J9>=500,"Medium","Small")) | M9: =_xlfn.IFS(J9>=1000,"Large",J9>=500,"Medium",TRUE,"Small") | N9: =IF(AND(D9="Dhaka",J9>=1000),"Priority","Normal") | O9: =IF(OR(I9="Shipped",I9="Pending"),"Follow up","") | P9: =IF(AND(I9="Delivered",J9>=1000),"Key delivery","-") | Q9: =_xlfn.XLOOKUP(F9,Products!$A$2:$A$7,Products!$C$2:$C$7,"Not found") | R9: =INDEX(Products!$C$2:$C$7,MATCH(F9,Products!$A$2:$A$7,0)) | S9: =1-H9/R9 | T9: =INDEX(Customers!$C$2:$C$7,MATCH(C9,Customers!$B$2:$B$7,0)) | U9: =INDEX(Products!$D$2:$D$7,MATCH(F9,Products!$A$2:$A$7,0))
A10: 9 | B10: 46071 | C10: Sun Fashion | D10: Narayanganj | E10: Fabric | F10: Denim 12oz | G10: 150 | H10: 5.4 | I10: Pending | J10: =G10*H10 | K10: =IF(I10="Cancelled","No","Yes") | L10: =IF(J10>=1000,"Large",IF(J10>=500,"Medium","Small")) | M10: =_xlfn.IFS(J10>=1000,"Large",J10>=500,"Medium",TRUE,"Small") | N10: =IF(AND(D10="Dhaka",J10>=1000),"Priority","Normal") | O10: =IF(OR(I10="Shipped",I10="Pending"),"Follow up","") | P10: =IF(AND(I10="Delivered",J10>=1000),"Key delivery","-") | Q10: =_xlfn.XLOOKUP(F10,Products!$A$2:$A$7,Products!$C$2:$C$7,"Not found") | R10: =INDEX(Products!$C$2:$C$7,MATCH(F10,Products!$A$2:$A$7,0)) | S10: =1-H10/R10 | T10: =INDEX(Customers!$C$2:$C$7,MATCH(C10,Customers!$B$2:$B$7,0)) | U10: =INDEX(Products!$D$2:$D$7,MATCH(F10,Products!$A$2:$A$7,0))
A11: 10 | B11: 46078 | C11: Rahim Traders | D11: Dhaka | E11: Yarn | F11: Cotton Yarn 30s | G11: 300 | H11: 2.9 | I11: Delivered | J11: =G11*H11 | K11: =IF(I11="Cancelled","No","Yes") | L11: =IF(J11>=1000,"Large",IF(J11>=500,"Medium","Small")) | M11: =_xlfn.IFS(J11>=1000,"Large",J11>=500,"Medium",TRUE,"Small") | N11: =IF(AND(D11="Dhaka",J11>=1000),"Priority","Normal") | O11: =IF(OR(I11="Shipped",I11="Pending"),"Follow up","") | P11: =IF(AND(I11="Delivered",J11>=1000),"Key delivery","-") | Q11: =_xlfn.XLOOKUP(F11,Products!$A$2:$A$7,Products!$C$2:$C$7,"Not found") | R11: =INDEX(Products!$C$2:$C$7,MATCH(F11,Products!$A$2:$A$7,0)) | S11: =1-H11/R11 | T11: =INDEX(Customers!$C$2:$C$7,MATCH(C11,Customers!$B$2:$B$7,0)) | U11: =INDEX(Products!$D$2:$D$7,MATCH(F11,Products!$A$2:$A$7,0))
A12: 11 | B12: 46084 | C12: Sun Fashion | D12: Narayanganj | E12: Trims | F12: Zippers | G12: 1500 | H12: 0.28 | I12: Delivered | J12: =G12*H12 | K12: =IF(I12="Cancelled","No","Yes") | L12: =IF(J12>=1000,"Large",IF(J12>=500,"Medium","Small")) | M12: =_xlfn.IFS(J12>=1000,"Large",J12>=500,"Medium",TRUE,"Small") | N12: =IF(AND(D12="Dhaka",J12>=1000),"Priority","Normal") | O12: =IF(OR(I12="Shipped",I12="Pending"),"Follow up","") | P12: =IF(AND(I12="Delivered",J12>=1000),"Key delivery","-") | Q12: =_xlfn.XLOOKUP(F12,Products!$A$2:$A$7,Products!$C$2:$C$7,"Not found") | R12: =INDEX(Products!$C$2:$C$7,MATCH(F12,Products!$A$2:$A$7,0)) | S12: =1-H12/R12 | T12: =INDEX(Customers!$C$2:$C$7,MATCH(C12,Customers!$B$2:$B$7,0)) | U12: =INDEX(Products!$D$2:$D$7,MATCH(F12,Products!$A$2:$A$7,0))
A13: 12 | B13: 46090 | C13: Karim Garments | D13: Chattogram | E13: Fabric | F13: Denim 12oz | G13: 250 | H13: 5.1 | I13: Shipped | J13: =G13*H13 | K13: =IF(I13="Cancelled","No","Yes") | L13: =IF(J13>=1000,"Large",IF(J13>=500,"Medium","Small")) | M13: =_xlfn.IFS(J13>=1000,"Large",J13>=500,"Medium",TRUE,"Small") | N13: =IF(AND(D13="Dhaka",J13>=1000),"Priority","Normal") | O13: =IF(OR(I13="Shipped",I13="Pending"),"Follow up","") | P13: =IF(AND(I13="Delivered",J13>=1000),"Key delivery","-") | Q13: =_xlfn.XLOOKUP(F13,Products!$A$2:$A$7,Products!$C$2:$C$7,"Not found") | R13: =INDEX(Products!$C$2:$C$7,MATCH(F13,Products!$A$2:$A$7,0)) | S13: =1-H13/R13 | T13: =INDEX(Customers!$C$2:$C$7,MATCH(C13,Customers!$B$2:$B$7,0)) | U13: =INDEX(Products!$D$2:$D$7,MATCH(F13,Products!$A$2:$A$7,0))

Sheet Products
A1: product | B1: category | C1: list_price | D1: supplier
A2: Cotton Twill | B2: Fabric | C2: 3.6 | D2: Meghna Mills
A3: Denim 12oz | B3: Fabric | C3: 5.5 | D3: Padma Denim
A4: Metal Buttons | B4: Trims | C4: 0.05 | D4: Star Trims
A5: Zippers | B5: Trims | C5: 0.32 | D5: Star Trims
A6: Cotton Yarn 30s | B6: Yarn | C6: 3 | D6: Jamuna Spinning
A7: Polyester Yarn | B7: Yarn | C7: 2.2 | D7: Jamuna Spinning

Sheet Customers
A1: customer_id | B1: customer_name | C1: segment | D1: city | E1: account_manager
A2: 1 | B2: Rahim Traders | C2: Trader | D2: Dhaka | E2: Anika
A3: 2 | B3: Karim Garments | C3: Garment Factory | D3: Chattogram | E3: Tanvir
A4: 3 | B4: Nova Apparel | C4: Garment Factory | D4: Dhaka | E4: Anika
A5: 4 | B5: Delta Knit | C5: Knitting Mill | D5: Gazipur | E5: Tanvir
A6: 5 | B6: Sun Fashion | C6: Garment Factory | D6: Narayanganj | E6: Anika
A7: 6 | B7: Blue Thread Ltd | C7: Trader | D7: Dhaka | E7: Tanvir

Sheet Summary
A1: region | B1: net_revenue | C1: net_orders | E1: category | F1: net_revenue | G1: net_orders
A2: Dhaka | B2: =SUMIFS('Orders (solved)'!$J$2:$J$13,'Orders (solved)'!$D$2:$D$13,A2,'Orders (solved)'!$I$2:$I$13,"<>Cancelled") | C2: =COUNTIFS('Orders (solved)'!$D$2:$D$13,A2,'Orders (solved)'!$I$2:$I$13,"<>Cancelled") | E2: Fabric | F2: =SUMIFS('Orders (solved)'!$J$2:$J$13,'Orders (solved)'!$E$2:$E$13,E2,'Orders (solved)'!$I$2:$I$13,"<>Cancelled") | G2: =COUNTIFS('Orders (solved)'!$E$2:$E$13,E2,'Orders (solved)'!$I$2:$I$13,"<>Cancelled")
A3: Gazipur | B3: =SUMIFS('Orders (solved)'!$J$2:$J$13,'Orders (solved)'!$D$2:$D$13,A3,'Orders (solved)'!$I$2:$I$13,"<>Cancelled") | C3: =COUNTIFS('Orders (solved)'!$D$2:$D$13,A3,'Orders (solved)'!$I$2:$I$13,"<>Cancelled") | E3: Yarn | F3: =SUMIFS('Orders (solved)'!$J$2:$J$13,'Orders (solved)'!$E$2:$E$13,E3,'Orders (solved)'!$I$2:$I$13,"<>Cancelled") | G3: =COUNTIFS('Orders (solved)'!$E$2:$E$13,E3,'Orders (solved)'!$I$2:$I$13,"<>Cancelled")
A4: Chattogram | B4: =SUMIFS('Orders (solved)'!$J$2:$J$13,'Orders (solved)'!$D$2:$D$13,A4,'Orders (solved)'!$I$2:$I$13,"<>Cancelled") | C4: =COUNTIFS('Orders (solved)'!$D$2:$D$13,A4,'Orders (solved)'!$I$2:$I$13,"<>Cancelled") | E4: Trims | F4: =SUMIFS('Orders (solved)'!$J$2:$J$13,'Orders (solved)'!$E$2:$E$13,E4,'Orders (solved)'!$I$2:$I$13,"<>Cancelled") | G4: =COUNTIFS('Orders (solved)'!$E$2:$E$13,E4,'Orders (solved)'!$I$2:$I$13,"<>Cancelled")
A5: Narayanganj | B5: =SUMIFS('Orders (solved)'!$J$2:$J$13,'Orders (solved)'!$D$2:$D$13,A5,'Orders (solved)'!$I$2:$I$13,"<>Cancelled") | C5: =COUNTIFS('Orders (solved)'!$D$2:$D$13,A5,'Orders (solved)'!$I$2:$I$13,"<>Cancelled")
A6: Total | B6: =SUM(B2:B5) | C6: =SUM(C2:C5)
A9: check | B9: result
A10: February 2026 net revenue | B10: =SUMIFS('Orders (solved)'!$J$2:$J$13,'Orders (solved)'!$B$2:$B$13,">="&DATE(2026,2,1),'Orders (solved)'!$B$2:$B$13,"<"&DATE(2026,3,1),'Orders (solved)'!$I$2:$I$13,"<>Cancelled")
A11: Average Fabric order (net) | B11: =AVERAGEIFS('Orders (solved)'!$J$2:$J$13,'Orders (solved)'!$E$2:$E$13,"Fabric",'Orders (solved)'!$I$2:$I$13,"<>Cancelled")
A12: Orders for Cotton* products | B12: =COUNTIFS('Orders (solved)'!$F$2:$F$13,"Cotton*")
A13: Orders counted as sales | B13: =COUNTIF('Orders (solved)'!$K$2:$K$13,"Yes")
A14: Orders for Star Trims products | B14: =COUNTIF('Orders (solved)'!$U$2:$U$13,"Star Trims")
A15: Average order value (net) | B15: =SUMIFS('Orders (solved)'!$J$2:$J$13,'Orders (solved)'!$I$2:$I$13,"<>Cancelled")/COUNTIFS('Orders (solved)'!$I$2:$I$13,"<>Cancelled")
A16: Average of all 12 values (incl. cancelled) | B16: =AVERAGE('Orders (solved)'!$J$2:$J$13)
A17: CHECK: region total = all net revenue | B17: =IF(B6=SUMIFS('Orders (solved)'!$J$2:$J$13,'Orders (solved)'!$I$2:$I$13,"<>Cancelled"),"OK","MISMATCH")

Sheet FILTER & LET
A1: Type these formulas into cell L2 of the Orders sheet (Microsoft 365 / Excel 2021+).
A2: Task | B2: Formula (type it, don't paste as text) | C2: Expected result
A3: Non-cancelled Dhaka orders | B3: =FILTER(A2:J13,(D2:D13="Dhaka")*(I2:I13<>"Cancelled"),"No orders") | C3: Orders 1, 3, 7, 10
A4: Shipped or Pending | B4: =FILTER(A2:J13,(I2:I13="Shipped")+(I2:I13="Pending"),"None") | C4: Orders 7, 9, 12
A5: Dhaka, sorted by value | B5: =SORT(FILTER(A2:J13,(D2:D13="Dhaka")*(I2:I13<>"Cancelled"),"No orders"),10,-1) | C5: Orders 3, 10, 1, 7
A6: Exercise: Fabric > 700, not cancelled | B6: =SORT(FILTER(A2:J13,(E2:E13="Fabric")*(J2:J13>700)*(I2:I13<>"Cancelled"),"None"),10,-1) | C6: Orders 3, 12, 9
A7: Average order value with LET | B7: =LET(revenue,SUMIFS(J2:J13,I2:I13,"<>Cancelled"),orders,COUNTIFS(I2:I13,"<>Cancelled"),revenue/orders) | C7: 825

Sheet Model
A1: Base revenue (non-cancelled) | B1: =SUMIFS('Orders (solved)'!$J$2:$J$13,'Orders (solved)'!$I$2:$I$13,"<>Cancelled") | D1: Scenario grid — same result as Data → What-If Analysis → Data Table (rows: volume, columns: price)
A2: Price change (input) | B2: 0 | D2: volume ↓ / price → | E2: 0 | F2: 0.05 | G2: 0.1
A3: Volume change (input) | B3: 0 | D3: 0 | E3: =$B$1*(1+E$2)*(1+$D3) | F3: =$B$1*(1+F$2)*(1+$D3) | G3: =$B$1*(1+G$2)*(1+$D3)
A4: Projected revenue | B4: =B1*(1+B2)*(1+B3) | D4: -0.05 | E4: =$B$1*(1+E$2)*(1+$D4) | F4: =$B$1*(1+F$2)*(1+$D4) | G4: =$B$1*(1+G$2)*(1+$D4)
D5: -0.1 | E5: =$B$1*(1+E$2)*(1+$D5) | F5: =$B$1*(1+F$2)*(1+$D5) | G5: =$B$1*(1+G$2)*(1+$D5)
A7: Goal Seek answers
A8: Price change for 10,000 revenue at −5% volume | B8: =10000/(B1*0.95)-1
A9: Volume change that keeps 9,075 after +10% price | B9: =1/1.1-1
A10: Denim units for a 1,000 order at 5.40 (round up in practice) | B10: =1000/5.4
